ai_ops/__init__.py
ai_ops/agents/__init__.py
ai_ops/agents/multi_mcp_agent.py
ai_ops/agents/simple_agent.py
ai_ops/agents/single_mcp_agent.py
ai_ops/api/__init__.py
ai_ops/api/serializers.py
ai_ops/api/urls.py
ai_ops/api/views.py
ai_ops/app-config-schema.json
ai_ops/banner.py
ai_ops/celery_tasks.py
ai_ops/checkpointer.py
ai_ops/constants/middleware_schemas.py
ai_ops/filters.py
ai_ops/forms.py
ai_ops/helpers/USAGE_EXAMPLES.md
ai_ops/helpers/async_shutdown.py
ai_ops/helpers/common/__init__.py
ai_ops/helpers/common/apihandler.py
ai_ops/helpers/common/asyncio_utils.py
ai_ops/helpers/common/constants.py
ai_ops/helpers/common/encoders.py
ai_ops/helpers/common/enums.py
ai_ops/helpers/common/exceptions.py
ai_ops/helpers/common/helpers.py
ai_ops/helpers/get_azure_model.py
ai_ops/helpers/get_info.py
ai_ops/helpers/get_llm_model.py
ai_ops/helpers/get_middleware.py
ai_ops/helpers/get_prompt.py
ai_ops/helpers/job_utils.py
ai_ops/helpers/langgraph_serializers.py
ai_ops/helpers/llm_providers/__init__.py
ai_ops/helpers/llm_providers/anthropic.py
ai_ops/helpers/llm_providers/azure_ai.py
ai_ops/helpers/llm_providers/base.py
ai_ops/helpers/llm_providers/huggingface.py
ai_ops/helpers/llm_providers/ollama.py
ai_ops/helpers/llm_providers/openai.py
ai_ops/helpers/logging_config.py
ai_ops/helpers/tool_callback.py
ai_ops/jobs/__init__.py
ai_ops/jobs/chat_session_cleanup.py
ai_ops/jobs/checkpoint_cleanup.py
ai_ops/jobs/mcp_health_check.py
ai_ops/migrations/0001_initial.py
ai_ops/migrations/0002_remove_llmmiddleware_ttl_and_more.py
ai_ops/migrations/0003_systemprompt_llmmodel_system_prompt.py
ai_ops/migrations/__init__.py
ai_ops/models.py
ai_ops/navigation.py
ai_ops/prompts/REFACTOR_SUMMARY.md
ai_ops/prompts/template_renderer.py
ai_ops/prompts/templates/README.md
ai_ops/prompts/templates/multi_mcp_system_prompt.md
ai_ops/prompts/templates/system_prompt.md
ai_ops/signals.py
ai_ops/static/ai_ops/css/chat_widget.css
ai_ops/static/ai_ops/css/system_prompt.css
nautobot_ai_ops-1.0.6.dist-info/LICENSE
nautobot_ai_ops-1.0.6.dist-info/METADATA
nautobot_ai_ops-1.0.6.dist-info/WHEEL
nautobot_ai_ops-1.0.6.dist-info/RECORD
