Metadata-Version: 2.3
Name: nautobot-ai-ops
Version: 1.0.6
Summary: AI Ops - Advanced artificial intelligence capabilities for Nautobot through multi-provider LLM architecture and Model Context Protocol
License: Apache-2.0
Keywords: nautobot,nautobot-app,nautobot-plugin,ai,llm,langchain,langgraph,mcp
Author: Kevin Campos
Author-email: kvncampos@duck.com
Requires-Python: >=3.10,<3.13
Classifier: Development Status :: 5 - Production/Stable
Classifier: Framework :: Django
Classifier: Intended Audience :: Developers
Classifier: License :: OSI Approved :: Apache Software License
Classifier: Programming Language :: Python :: 3
Classifier: Programming Language :: Python :: 3.10
Classifier: Programming Language :: Python :: 3.11
Classifier: Programming Language :: Python :: 3.12
Classifier: Topic :: System :: Networking
Provides-Extra: all
Requires-Dist: Jinja2 (>=3.1.0,<4.0.0)
Requires-Dist: langchain (>=1.1.0,<2.0.0)
Requires-Dist: langchain-anthropic (>=1.3.0,<2.0.0)
Requires-Dist: langchain-core (>=1.2.5,<2.0.0)
Requires-Dist: langchain-huggingface (>=1.2.0,<2.0.0)
Requires-Dist: langchain-mcp-adapters (>=0.1.14,<0.2.0)
Requires-Dist: langchain-ollama (>=1.0.1,<2.0.0)
Requires-Dist: langchain-openai (>=1.1.0,<2.0.0)
Requires-Dist: langgraph (>=1.0.4,<2.0.0)
Requires-Dist: langgraph-checkpoint-redis (>=0.2.1,<0.3.0)
Requires-Dist: nautobot (>=3.0.0)
Requires-Dist: pydantic (>=2.0.0,<3.0.0)
Requires-Dist: python-json-logger (>=4.0.0,<5.0.0)
Project-URL: Bug Tracker, https://github.com/kvncampos/nautobot-ai-ops/issues
Project-URL: Changelog, https://kvncampos.github.io/nautobot-ai-ops/admin/release_notes/
Project-URL: Documentation, https://kvncampos.github.io/nautobot-ai-ops/
Project-URL: Download, https://pypi.org/project/nautobot-ai-ops/#files
Project-URL: Homepage, https://github.com/kvncampos/nautobot-ai-ops
Project-URL: Repository, https://github.com/kvncampos/nautobot-ai-ops
